skopt/__init__.py
skopt/acquisition.py
skopt/benchmarks.py
skopt/callbacks.py
skopt/plots.py
skopt/searchcv.py
skopt/utils.py
skopt/learning/__init__.py
skopt/learning/forest.py
skopt/learning/gbrt.py
skopt/learning/gaussian_process/__init__.py
skopt/learning/gaussian_process/gpr.py
skopt/learning/gaussian_process/kernels.py
skopt/optimizer/__init__.py
skopt/optimizer/base.py
skopt/optimizer/dummy.py
skopt/optimizer/forest.py
skopt/optimizer/gbrt.py
skopt/optimizer/gp.py
skopt/optimizer/optimizer.py
skopt/sampler/__init__.py
skopt/sampler/base.py
skopt/sampler/grid.py
skopt/sampler/halton.py
skopt/sampler/hammersly.py
skopt/sampler/lhs.py
skopt/sampler/sobol.py
skopt/space/__init__.py
skopt/space/space.py
skopt/space/transformers.py
ts_scikit_optimize-0.9.2.dist-info/AUTHORS.md
ts_scikit_optimize-0.9.2.dist-info/LICENSE
ts_scikit_optimize-0.9.2.dist-info/METADATA
ts_scikit_optimize-0.9.2.dist-info/WHEEL
ts_scikit_optimize-0.9.2.dist-info/top_level.txt
ts_scikit_optimize-0.9.2.dist-info/RECORD
