Metadata-Version: 2.1
Name: ts-scikit-optimize
Version: 0.9.2
Summary: Sequential model-based optimization toolbox.
Home-page: https://scikit-optimize.github.io/
Author: The scikit-optimize contributors, the KhulnaSoft Team
License: BSD 3-clause
Classifier: Development Status :: 5 - Production/Stable
Classifier: Intended Audience :: Science/Research
Classifier: Intended Audience :: Developers
Classifier: License :: OSI Approved :: BSD License
Classifier: Programming Language :: Python :: 3
Classifier: Topic :: Scientific/Engineering :: Artificial Intelligence
Classifier: Topic :: Scientific/Engineering :: Visualization
Classifier: Topic :: Software Development :: Libraries :: Python Modules
Classifier: Operating System :: MacOS
Classifier: Operating System :: Microsoft :: Windows
Classifier: Operating System :: OS Independent
Classifier: Operating System :: POSIX
Classifier: Operating System :: Unix
Requires-Python: >= 3.8
License-File: LICENSE
License-File: AUTHORS.md
Requires-Dist: joblib >=1.2
Requires-Dist: pyaml >=16.9
Requires-Dist: numpy >=1.17
Requires-Dist: scipy >=1.5
Requires-Dist: scikit-learn >1.1
Provides-Extra: dev
Requires-Dist: flake8 ; extra == 'dev'
Requires-Dist: pytest ; extra == 'dev'
Requires-Dist: pytest-cov ; extra == 'dev'
Requires-Dist: pytest-xdist ; extra == 'dev'
Provides-Extra: doc
Requires-Dist: sphinx ; extra == 'doc'
Requires-Dist: sphinx-gallery >=0.6 ; extra == 'doc'
Requires-Dist: memory-profiler ; extra == 'doc'
Requires-Dist: numpydoc ; extra == 'doc'
Provides-Extra: plots
Requires-Dist: matplotlib >=2.0.0 ; extra == 'plots'
